solvers/HHT_solver.py
solvers/__init__.py
solvers/base_solver.py
solvers/bathe_solver.py
solvers/central_difference_solver.py
solvers/newmark_solver.py
solvers/static_solver.py
solvers/utils.py
solvers/zhai_solver.py
pugglesolvers-1.0.1.dist-info/METADATA
pugglesolvers-1.0.1.dist-info/WHEEL
pugglesolvers-1.0.1.dist-info/top_level.txt
pugglesolvers-1.0.1.dist-info/RECORD
