Metadata-Version: 2.4
Name: PuggleSolvers
Version: 1.0.1
Summary: Numerical solvers
Author: Bruno Zuada Coelho, Aron Noordam
Author-email: bruno.zuadacoelho@deltares.nl, aron.noordam@deltares.nl
Classifier: Programming Language :: Python :: 3
Classifier: License :: OSI Approved :: MIT License
Classifier: Operating System :: OS Independent
Requires-Python: >=3.9
Requires-Dist: numpy>=1.18.1
Requires-Dist: scipy>=1.4.1
Requires-Dist: tqdm>=4.46.0
Provides-Extra: testing
Requires-Dist: pytest>=6.0; extra == "testing"
Requires-Dist: pytest-cov>=2.0; extra == "testing"
Requires-Dist: tox>=3.24; extra == "testing"
